rss3_dsl_client/__init__.py
rss3_dsl_client/client.py
rss3_dsl_client/schemas/__init__.py
rss3_dsl_client/schemas/collectible.py
rss3_dsl_client/schemas/common.py
rss3_dsl_client/schemas/enums.py
rss3_dsl_client/schemas/exchange.py
rss3_dsl_client/schemas/metaverse.py
rss3_dsl_client/schemas/rss.py
rss3_dsl_client/schemas/social.py
rss3_dsl_client/schemas/transaction.py
rss3_dsl_client-0.3.0.dist-info/LICENSE
rss3_dsl_client-0.3.0.dist-info/METADATA
rss3_dsl_client-0.3.0.dist-info/WHEEL
rss3_dsl_client-0.3.0.dist-info/RECORD
